CHANGES.txt
LICENSE.txt
MANIFEST.in
PackageInfo.cfg
README.rst
setup.cfg
setup.py
html/genindex.html
html/index.html
html/objects.inv
html/search.html
html/searchindex.js
html/_sources/index.txt
html/_static/ajax-loader.gif
html/_static/basic.css
html/_static/comment-bright.png
html/_static/comment-close.png
html/_static/comment.png
html/_static/default.css
html/_static/doctools.js
html/_static/down-pressed.png
html/_static/down.png
html/_static/file.png
html/_static/jquery.js
html/_static/minus.png
html/_static/plus.png
html/_static/pygments.css
html/_static/searchtools.js
html/_static/sidebar.js
html/_static/underscore.js
html/_static/up-pressed.png
html/_static/up.png
html/_static/websupport.js
radialx/__init__.py
radialx/_radialx.py
radialx/_version.py
radialx/check_config.py
radialx/distmat.py
radialx/headerx.py
radialx/ordereddict.py
radialx/powderx.py
radialx/profilex.py
radialx/signals.py
radialx.egg-info/PKG-INFO
radialx.egg-info/SOURCES.txt
radialx.egg-info/dependency_links.txt
radialx.egg-info/requires.txt
radialx.egg-info/top_level.txt