Metadata-Version: 1.1
Name: radialx
Version: 0.8.14
Summary: A python package for powder diffraction
Home-page: http://pypi.python.org/pypi/radialx
Author: James C. Stroud
Author-email: xtald00d@gmail.com
License: BSD
Platform: UNKNOWN
Classifier: Programming Language :: Python :: 2.6
Classifier: Programming Language :: Python :: 2.7
